bilibili_live/__init__.py
bilibili_live/api/__init__.py
bilibili_live/api/generateLoginQRCode.py
bilibili_live/api/getDanmuInfo.py
bilibili_live/api/getRoomInfo.py
bilibili_live/api/getUserInfo.py
bilibili_live/api/pullScanCodeStatus.py
bilibili_live/bilibiliLive.py
bilibili_live/events/__init__.py
bilibili_live/events/eventData.py
bilibili_live/events/handler.py
bilibili_live/login.py
bilibili_live/packageProcess/convert/DANMU_MSG_to_Danmu.py
bilibili_live/packageProcess/convert/ENTRY_EFFECT_to_User.py
bilibili_live/packageProcess/convert/GUARD_BUY_to_User.py
bilibili_live/packageProcess/convert/INTERACT_WORD_to_User.py
bilibili_live/packageProcess/convert/SEND_GIFT_to_Gift.py
bilibili_live/packageProcess/convert/SUPER_CHAT_MESSAGE_JPN_to_SuperChat.py
bilibili_live/packageProcess/convert/SUPER_CHAT_MESSAGE_to_SuperChat.py
bilibili_live/packageProcess/exceptions.py
bilibili_live/packageProcess/packageProcessor.py
bilibili_live/proto/proto.py
bilibili_live-0.10.4.dist-info/WHEEL
bilibili_live-0.10.4.dist-info/METADATA
bilibili_live-0.10.4.dist-info/licenses/LICENSE
bilibili_live-0.10.4.dist-info/RECORD
