Metadata-Version: 2.1
Name: bilibili-live
Version: 0.10.4
Summary: 哔哩哔哩直播间互动工具
License: MIT
Author-email: Gedoy <773673499@qq.com>
Requires-Python: >=3.7
Requires-Dist: brotli>=1.0.9
Requires-Dist: qrcode>=7.3.1
Requires-Dist: requests>=2.28.1
Requires-Dist: websockets>=10.3
Project-URL: repository, https://github.com/Gedoy9793/bilibili-live
